{
    "character": "𠼦",
    "details": {
        "Âm Hán Việt": [
            "mạn"
        ],
        "Tổng nét": [
            "14"
        ],
        "Bộ": [
            "khẩu 口 (+11 nét)"
        ],
        "Hình thái": [
            "⿰口曼"
        ],
        "Nét bút": [
            "丨フ一丨フ一一丨フ丨丨一フ丶"
        ],
        "Thương Hiệt": [
            "RAWE (口日田水)"
        ],
        "Unicode": [
            "U+20F26"
        ],
        "Độ thông dụng trong Hán ngữ cổ": [
            "rất thấp"
        ],
        "Độ thông dụng trong tiếng Trung hiện đại": [
            "rất thấp"
        ],
        "Âm Nôm": [
            "mặn",
            "mướn"
        ],
        "Âm Quảng Đông": [
            "maan4"
        ]
    },
    "meanings": {}
}