{
    "character": "𠞧",
    "details": {
        "Âm Hán Việt": [
            "ma",
            "mị",
            "mỹ"
        ],
        "Tổng nét": [
            "13"
        ],
        "Bộ": [
            "đao 刀 (+11 nét)"
        ],
        "Hình thái": [
            "⿸麻刀"
        ],
        "Nét bút": [
            "丶一ノ一丨ノフ一丨ノフフノ"
        ],
        "Unicode": [
            "U+207A7"
        ],
        "Độ thông dụng trong Hán ngữ cổ": [
            "rất thấp"
        ],
        "Độ thông dụng trong tiếng Trung hiện đại": [
            "rất thấp"
        ]
    },
    "meanings": {}
}