{
    "character": "𠙗",
    "details": {
        "Âm Hán Việt": [
            "phong",
            "phúng"
        ],
        "Tổng nét": [
            "10"
        ],
        "Bộ": [
            "kỷ 几 (+8 nét)",
            "xuyên 巛 (+7 nét)"
        ],
        "Hình thái": [
            "⿵⺇⿳天一巛"
        ],
        "Nét bút": [
            "ノフ一一ノ丶一フフフ"
        ],
        "Unicode": [
            "U+20657"
        ],
        "Độ thông dụng trong Hán ngữ cổ": [
            "rất thấp"
        ],
        "Độ thông dụng trong tiếng Trung hiện đại": [
            "rất thấp"
        ]
    },
    "meanings": {}
}