{
    "character": "𠕍",
    "details": {
        "Âm Hán Việt": [
            "quan"
        ],
        "Tổng nét": [
            "6"
        ],
        "Bộ": [
            "quynh 冂 (+4 nét)"
        ],
        "Hình thái": [
            "⿱丶⿵冂𢌬"
        ],
        "Nét bút": [
            "丶丨フ一ノフ"
        ],
        "Unicode": [
            "U+2054D"
        ],
        "Độ thông dụng trong Hán ngữ cổ": [
            "rất thấp"
        ],
        "Độ thông dụng trong tiếng Trung hiện đại": [
            "rất thấp"
        ]
    },
    "meanings": {}
}