{
    "character": "𠛞",
    "details": {
        "Âm Hán Việt": [
            "bổn",
            "hãng",
            "kháng"
        ],
        "Tổng nét": [
            "7"
        ],
        "Bộ": [
            "đao 刀 (+5 nét)"
        ],
        "Hình thái": [
            "⿱𡗜刀"
        ],
        "Nét bút": [
            "一ノ丶丶ノフノ"
        ],
        "Unicode": [
            "U+206DE"
        ],
        "Độ thông dụng trong Hán ngữ cổ": [
            "rất thấp"
        ],
        "Độ thông dụng trong tiếng Trung hiện đại": [
            "rất thấp"
        ]
    },
    "meanings": {}
}