{
    "character": "𡤩",
    "details": {
        "Âm Hán Việt": [
            "diễm"
        ],
        "Tổng nét": [
            "22"
        ],
        "Bộ": [
            "nữ 女 (+19 nét)"
        ],
        "Hình thái": [
            "⿰女艶"
        ],
        "Nét bút": [
            "フノ一丨フ一丨丨一一丨フ一丶ノ一ノフフ丨一フ"
        ],
        "Unicode": [
            "U+21929"
        ],
        "Độ thông dụng trong Hán ngữ cổ": [
            "rất thấp"
        ],
        "Độ thông dụng trong tiếng Trung hiện đại": [
            "rất thấp"
        ]
    },
    "meanings": {}
}