{
    "character": "𣇶",
    "details": {
        "Âm Hán Việt": [
            "một"
        ],
        "Tổng nét": [
            "12"
        ],
        "Bộ": [
            "nhật 日 (+8 nét)"
        ],
        "Hình thái": [
            "⿳⿰彐彐冖日"
        ],
        "Nét bút": [
            "フ一一フ一一丶フ丨フ一一"
        ],
        "Unicode": [
            "U+231F6"
        ],
        "Độ thông dụng trong Hán ngữ cổ": [
            "rất thấp"
        ],
        "Độ thông dụng trong tiếng Trung hiện đại": [
            "rất thấp"
        ]
    },
    "meanings": {}
}