{
    "character": "𥥍",
    "details": {
        "Âm Hán Việt": [
            "thâm"
        ],
        "Tổng nét": [
            "10"
        ],
        "Bộ": [
            "huyệt 穴 (+5 nét)"
        ],
        "Hình thái": [
            "⿱穴𡗜"
        ],
        "Nét bút": [
            "丶丶フノフ一ノ丶丶ノ"
        ],
        "Unicode": [
            "U+2594D"
        ],
        "Độ thông dụng trong Hán ngữ cổ": [
            "rất thấp"
        ],
        "Độ thông dụng trong tiếng Trung hiện đại": [
            "rất thấp"
        ]
    },
    "meanings": {}
}