{
    "character": "𥴈",
    "details": {
        "Tổng nét": [
            "18"
        ],
        "Bộ": [
            "trúc 竹 (+12 nét)"
        ],
        "Hình thái": [
            "⿱⺮棧"
        ],
        "Nét bút": [
            "ノ一丶ノ一丶一丨ノ丶一フノ丶一フノ丶"
        ],
        "Unicode": [
            "U+25D08"
        ],
        "Độ thông dụng trong Hán ngữ cổ": [
            "rất thấp"
        ],
        "Độ thông dụng trong tiếng Trung hiện đại": [
            "rất thấp"
        ]
    },
    "meanings": {}
}