{
    "character": "𥔢",
    "details": {
        "Tổng nét": [
            "13"
        ],
        "Bộ": [
            "thạch 石 (+8 nét)"
        ],
        "Hình thái": [
            "⿰石臾"
        ],
        "Nét bút": [
            "一ノ丨フ一ノ丨一一フ一一ノ丶"
        ],
        "Unicode": [
            "U+25522"
        ],
        "Độ thông dụng trong Hán ngữ cổ": [
            "rất thấp"
        ],
        "Độ thông dụng trong tiếng Trung hiện đại": [
            "rất thấp"
        ]
    },
    "meanings": {}
}