{
    "character": "𥮅",
    "details": {
        "Âm Hán Việt": [
            "toán"
        ],
        "Tổng nét": [
            "13"
        ],
        "Bộ": [
            "trúc 竹 (+7 nét)"
        ],
        "Hình thái": [
            "⿱⺮⿱王大"
        ],
        "Nét bút": [
            "ノ一丶ノ一丶一一丨一一ノ丶"
        ],
        "Unicode": [
            "U+25B85"
        ],
        "Độ thông dụng trong Hán ngữ cổ": [
            "rất thấp"
        ],
        "Độ thông dụng trong tiếng Trung hiện đại": [
            "rất thấp"
        ]
    },
    "meanings": {}
}