{
    "character": "𧖸",
    "details": {
        "Âm Hán Việt": [
            "minh"
        ],
        "Tổng nét": [
            "13"
        ],
        "Bộ": [
            "huyết 血 (+7 nét)"
        ],
        "Hình thái": [
            "⿱囧血"
        ],
        "Nét bút": [
            "丨フノフ丨フ一ノ丨フ丨丨一"
        ],
        "Unicode": [
            "U+275B8"
        ],
        "Độ thông dụng trong Hán ngữ cổ": [
            "rất thấp"
        ],
        "Độ thông dụng trong tiếng Trung hiện đại": [
            "rất thấp"
        ]
    },
    "meanings": {}
}