{
    "character": "𧣪",
    "details": {
        "Tổng nét": [
            "14"
        ],
        "Bộ": [
            "giác 角 (+7 nét)"
        ],
        "Hình thái": [
            "⿰角肖"
        ],
        "Nét bút": [
            "ノフノフ一一丨丨丶ノノフ丶一"
        ],
        "Unicode": [
            "U+278EA"
        ],
        "Độ thông dụng trong Hán ngữ cổ": [
            "rất thấp"
        ],
        "Độ thông dụng trong tiếng Trung hiện đại": [
            "rất thấp"
        ]
    },
    "meanings": {}
}