{
    "character": "𧐆",
    "details": {
        "Tổng nét": [
            "15"
        ],
        "Bộ": [
            "trùng 虫 (+9 nét)"
        ],
        "Hình thái": [
            "⿱既虫"
        ],
        "Nét bút": [
            "フ一一フ丶一フノフ丨フ一丨一丶"
        ],
        "Unicode": [
            "U+27406"
        ],
        "Độ thông dụng trong Hán ngữ cổ": [
            "rất thấp"
        ],
        "Độ thông dụng trong tiếng Trung hiện đại": [
            "rất thấp"
        ]
    },
    "meanings": {}
}