{
    "character": "𨖦",
    "details": {
        "Âm Hán Việt": [
            "báo"
        ],
        "Tổng nét": [
            "14"
        ],
        "Bộ": [
            "sước 辵 (+11 nét)"
        ],
        "Hình thái": [
            "⿺⻌⿳⺤日廾"
        ],
        "Nét bút": [
            "ノ丶丶ノ丨フ一一一ノ丨丶フ丶"
        ],
        "Unicode": [
            "U+285A6"
        ],
        "Độ thông dụng trong Hán ngữ cổ": [
            "rất thấp"
        ],
        "Độ thông dụng trong tiếng Trung hiện đại": [
            "rất thấp"
        ]
    },
    "meanings": {}
}