{
    "character": "𨮹",
    "details": {
        "Âm Hán Việt": [
            "đích"
        ],
        "Tổng nét": [
            "22"
        ],
        "Bộ": [
            "kim 金 (+14 nét)"
        ],
        "Hình thái": [
            "⿰金適"
        ],
        "Nét bút": [
            "ノ丶一一丨丶ノ一丶一丶ノ丨フ一丨丨フ一丶フ丶"
        ],
        "Unicode": [
            "U+28BB9"
        ],
        "Độ thông dụng trong Hán ngữ cổ": [
            "rất thấp"
        ],
        "Độ thông dụng trong tiếng Trung hiện đại": [
            "rất thấp"
        ],
        "Âm Nôm": [
            "thích",
            "thiếc"
        ],
        "Âm Quảng Đông": [
            "dik1",
            "dik6"
        ]
    },
    "meanings": {}
}