{
    "character": "𩰡",
    "details": {
        "Tổng nét": [
            "15"
        ],
        "Bộ": [
            "sưởng 鬯 (+5 nét)"
        ],
        "Hình thái": [
            "⿰鬯史"
        ],
        "Nét bút": [
            "ノ丶丶丶丶丶フ丨一フ丨フ一ノ丶"
        ],
        "Unicode": [
            "U+29C21"
        ],
        "Độ thông dụng trong Hán ngữ cổ": [
            "rất thấp"
        ],
        "Độ thông dụng trong tiếng Trung hiện đại": [
            "rất thấp"
        ]
    },
    "meanings": {}
}