{
    "character": "𩏷",
    "details": {
        "Âm Hán Việt": [
            "thu",
            "tưu"
        ],
        "Tổng nét": [
            "27"
        ],
        "Bộ": [
            "vi 韋 (+18 nét)"
        ],
        "Hình thái": [
            "⿰⿱米韋焦"
        ],
        "Nét bút": [
            "丶ノ一丨ノ丶フ丨一丨フ一一フ丨ノ丨丶一一一丨一丶丶丶丶"
        ],
        "Unicode": [
            "U+293F7"
        ],
        "Độ thông dụng trong Hán ngữ cổ": [
            "rất thấp"
        ],
        "Độ thông dụng trong tiếng Trung hiện đại": [
            "rất thấp"
        ]
    },
    "meanings": {}
}