{
    "character": "𩠬",
    "details": {
        "Tổng nét": [
            "18"
        ],
        "Bộ": [
            "thủ 首 (+9 nét)"
        ],
        "Hình thái": [
            "⿰首首"
        ],
        "Nét bút": [
            "丶ノ一ノ丨フ一一一丶ノ一ノ丨フ一一一"
        ],
        "Unicode": [
            "U+2982C"
        ],
        "Độ thông dụng trong Hán ngữ cổ": [
            "rất thấp"
        ],
        "Độ thông dụng trong tiếng Trung hiện đại": [
            "rất thấp"
        ]
    },
    "meanings": {}
}