{
    "character": "𩃛",
    "details": {
        "Tổng nét": [
            "16"
        ],
        "Bộ": [
            "vũ 雨 (+8 nét)"
        ],
        "Hình thái": [
            "⿱雨昑"
        ],
        "Nét bút": [
            "一丶フ丨丶一ノ丶丨フ一一ノ丶一フ"
        ],
        "Unicode": [
            "U+290DB"
        ],
        "Độ thông dụng trong Hán ngữ cổ": [
            "rất thấp"
        ],
        "Độ thông dụng trong tiếng Trung hiện đại": [
            "rất thấp"
        ]
    },
    "meanings": {}
}