{
    "character": "㑒",
    "details": {
        "Âm Hán Việt": [
            "thiêm"
        ],
        "Tổng nét": [
            "8"
        ],
        "Bộ": [
            "nhân 人 (+6 nét)"
        ],
        "Hình thái": [
            "⿱亼央"
        ],
        "Nét bút": [
            "ノ丶一丨フ一ノ丶"
        ],
        "Thương Hiệt": [
            "OMLO (人一中人)"
        ],
        "Unicode": [
            "U+3452"
        ],
        "Độ thông dụng trong Hán ngữ cổ": [
            "rất thấp"
        ],
        "Độ thông dụng trong tiếng Trung hiện đại": [
            "rất thấp"
        ]
    },
    "meanings": {}
}