{
    "character": "㚼",
    "details": {
        "Âm Hán Việt": [
            "nữu"
        ],
        "Tổng nét": [
            "8"
        ],
        "Bộ": [
            "nữ 女 (+5 nét)"
        ],
        "Hình thái": [
            "⿰女田"
        ],
        "Nét bút": [
            "フノ一丨フ一丨一"
        ],
        "Thương Hiệt": [
            "VW (女田)"
        ],
        "Unicode": [
            "U+36BC"
        ],
        "Độ thông dụng trong Hán ngữ cổ": [
            "rất thấp"
        ],
        "Độ thông dụng trong tiếng Trung hiện đại": [
            "rất thấp"
        ],
        "Âm Quảng Đông": [
            "naau2"
        ]
    },
    "meanings": {}
}