{
    "character": "㘲",
    "details": {
        "Âm Hán Việt": [
            "ách",
            "ải"
        ],
        "Tổng nét": [
            "8"
        ],
        "Bộ": [
            "thổ 土 (+5 nét)"
        ],
        "Hình thái": [
            "⿰土尻"
        ],
        "Nét bút": [
            "一丨一フ一ノノフ"
        ],
        "Thương Hiệt": [
            "GSKN (土尸大弓)"
        ],
        "Unicode": [
            "U+3632"
        ],
        "Độ thông dụng trong Hán ngữ cổ": [
            "rất thấp"
        ],
        "Độ thông dụng trong tiếng Trung hiện đại": [
            "rất thấp"
        ],
        "Âm Quảng Đông": [
            "guk1"
        ]
    },
    "meanings": {}
}