{
    "character": "䌸",
    "details": {
        "Âm Hán Việt": [
            "truyện"
        ],
        "Tổng nét": [
            "7"
        ],
        "Bộ": [
            "mịch 糸 (+4 nét)"
        ],
        "Hình thái": [
            "⿰⺰专"
        ],
        "Nét bút": [
            "フフ一一一フ丶"
        ],
        "Thương Hiệt": [
            "VMQNI (女一手弓戈)"
        ],
        "Unicode": [
            "U+4338"
        ],
        "Độ thông dụng trong Hán ngữ cổ": [
            "rất thấp"
        ],
        "Độ thông dụng trong tiếng Trung hiện đại": [
            "rất thấp"
        ],
        "Âm Pinyin": [
            "zhuàn ㄓㄨㄢˋ"
        ],
        "Âm Quảng Đông": [
            "gyun3"
        ]
    },
    "meanings": {}
}