{
    "character": "嘠",
    "details": {
        "Âm Hán Việt": [
            "dát"
        ],
        "Tổng nét": [
            "15"
        ],
        "Bộ": [
            "khẩu 口 (+12 nét)"
        ],
        "Hình thái": [
            "⿰口戞"
        ],
        "Nét bút": [
            "丨フ一一ノ丨フ一一丶フ一フノ丶"
        ],
        "Thương Hiệt": [
            "RMBI (口一月戈)"
        ],
        "Unicode": [
            "U+5620"
        ],
        "Độ thông dụng trong Hán ngữ cổ": [
            "rất thấp"
        ],
        "Độ thông dụng trong tiếng Trung hiện đại": [
            "rất thấp"
        ],
        "Âm Pinyin": [
            "gá ㄍㄚˊ"
        ],
        "Âm Quảng Đông": [
            "gaa1",
            "gaat3"
        ]
    },
    "meanings": {
        "dát": {
            "Từ điển phổ thông": [
                "một thứ binh khí như mâu",
                "gõ bằng gươm giáo"
            ]
        }
    }
}