{
    "character": "国",
    "details": {
        "Âm Hán Việt": [
            "quốc"
        ],
        "Tổng nét": [
            "8"
        ],
        "Bộ": [
            "vi 囗 (+5 nét)"
        ],
        "Lục thư": [
            "hội ý"
        ],
        "Hình thái": [
            "⿴囗玉"
        ],
        "Nét bút": [
            "丨フ一一丨一丶一"
        ],
        "Thương Hiệt": [
            "WMGI (田一土戈)"
        ],
        "Unicode": [
            "U+56FD"
        ],
        "Độ thông dụng trong Hán ngữ cổ": [
            "rất cao"
        ],
        "Độ thông dụng trong tiếng Trung hiện đại": [
            "rất cao"
        ],
        "Âm Pinyin": [
            "guó ㄍㄨㄛˊ"
        ],
        "Âm Nôm": [
            "quốc"
        ],
        "Âm Nhật (onyomi)": [
            "コク (koku)"
        ],
        "Âm Nhật (kunyomi)": [
            "くに (kuni)"
        ],
        "Âm Hàn": [
            "국"
        ],
        "Âm Quảng Đông": [
            "gwok3"
        ]
    },
    "meanings": {
        "quốc": {
            "Từ điển phổ thông": [
                "đất nước, quốc gia"
            ],
            "Từ điển trích dẫn": [
                "1. Giản thể của chữ 國."
            ],
            "Từ điển Trần Văn Chánh": [
                "Nước, quốc: 祖國 Tổ quốc; 外國 Nước ngoài; 保家衛國 Giữ nhà giữ nước; 國旗 Quốc kì; 國籍 Quốc tịch;",
                "(Của) Trung Quốc, trong nước: 國畫 Tranh Trung Quốc; 國產 Sản phẩm trong nước (do Trung Quốc sản xuất);",
                "[Guó] (Họ) Quốc."
            ],
            "Từ điển Nguyễn Quốc Hùng": [
                "Một lối viết của chữ Quốc 國."
            ],
            "compound_words": {
                "爱国": "ái quốc",
                "英国": "anh quốc",
                "报国": "báo quốc",
                "各国": "các quốc",
                "岛国": "đảo quốc",
                "帝国": "đế quốc",
                "东南亚国家联盟": "đông nam á quốc gia liên minh",
                "德国": "đức quốc",
                "美国": "mỹ quốc",
                "外国": "ngoại quốc",
                "法国": "pháp quốc",
                "国民": "quốc dân",
                "国营": "quốc doanh",
                "国家": "quốc gia",
                "国会": "quốc hội",
                "国有": "quốc hữu",
                "国库": "quốc khố",
                "国旗": "quốc kỳ",
                "国立": "quốc lập",
                "国力": "quốc lực",
                "国外": "quốc ngoại",
                "国內": "quốc nội",
                "国法": "quốc pháp",
                "国防": "quốc phòng",
                "国際": "quốc tế",
                "国籍": "quốc tịch",
                "国务": "quốc vụ",
                "国王": "quốc vương",
                "属国": "thuộc quốc",
                "全国": "toàn quốc",
                "中国": "trung quốc"
            }
        }
    }
}