{
    "character": "壘",
    "details": {
        "Âm Hán Việt": [
            "luật",
            "luỹ",
            "lỗi"
        ],
        "Tổng nét": [
            "18"
        ],
        "Bộ": [
            "thổ 土 (+15 nét)"
        ],
        "Lục thư": [
            "hình thanh & hội ý"
        ],
        "Hình thái": [
            "⿱畾土"
        ],
        "Nét bút": [
            "丨フ一丨一丨フ一丨一丨フ一丨一一丨一"
        ],
        "Thương Hiệt": [
            "WWWG (田田田土)"
        ],
        "Unicode": [
            "U+58D8"
        ],
        "Độ thông dụng trong Hán ngữ cổ": [
            "cao"
        ],
        "Độ thông dụng trong tiếng Trung hiện đại": [
            "cao"
        ],
        "Âm Pinyin": [
            "léi ㄌㄟˊ",
            "lěi ㄌㄟˇ",
            "lèi ㄌㄟˋ",
            "lù ㄌㄨˋ"
        ],
        "Âm Nôm": [
            "luỹ"
        ],
        "Âm Nhật (onyomi)": [
            "ルイ (rui)",
            "ライ (rai)",
            "スイ (sui)"
        ],
        "Âm Nhật (kunyomi)": [
            "とりで (toride)"
        ],
        "Âm Hàn": [
            "루",
            "뢰",
            "누"
        ],
        "Âm Quảng Đông": [
            "leoi5",
            "leot6"
        ]
    },
    "meanings": {
        "luật": {
            "Từ điển trích dẫn": [
                "(Danh) Bờ lũy, tường chắn trong dinh quân hoặc để che chở thành.",
                "(Danh) Họ 'Lũy'.",
                "(Đồng) Chồng chất, xếp đống (đất, đá, gạch...). § Thông 'lũy' 累. ◎Như: 'lũy tường' 壘牆 xây tường.",
                "Một âm là 'luật'. (Danh) 'Uất Luật' 鬱壘 tên một vị thần cổ (môn thần 門神, thần giữ cửa theo truyền thuyết). § Đời thượng cổ có hai anh em là Thần Đồ 神荼, Uất Luật 鬱壘 kiểm soát loài quỉ làm càn, bắt cho hổ ăn thịt, vì thế đời cho là vị thần trừ sự không lành, bây giờ hay thờ làm thần coi cửa."
            ],
            "Từ điển Thiều Chửu": [
                "Bờ luỹ, tức là tường chắn trong dinh quân.",
                "Một âm là luật. Uất Luật 鬱壘 tên một vị thần cổ. Ðời thượng cổ có hai anh em là Thần Ðồ 神荼, Uất Luật 鬱壘 kiểm soát loài quỷ làm càn, bắt cho hổ thịt, vì thế đời cho là vị thần trừ sự không lành, bây giờ hay thờ làm thần coi cửa, môn thần 門神."
            ],
            "Từ điển Nguyễn Quốc Hùng": [
                "Uất luật 欎壘: Tên một vị thần."
            ]
        },
        "luỹ": {
            "Từ điển phổ thông": [
                "thành đất cao",
                "xây cất"
            ],
            "Từ điển trích dẫn": [
                "(Danh) Bờ lũy, tường chắn trong dinh quân hoặc để che chở thành.",
                "(Danh) Họ 'Lũy'.",
                "(Đồng) Chồng chất, xếp đống (đất, đá, gạch...). § Thông 'lũy' 累. ◎Như: 'lũy tường' 壘牆 xây tường.",
                "Một âm là 'luật'. (Danh) 'Uất Luật' 鬱壘 tên một vị thần cổ (môn thần 門神, thần giữ cửa theo truyền thuyết). § Đời thượng cổ có hai anh em là Thần Đồ 神荼, Uất Luật 鬱壘 kiểm soát loài quỉ làm càn, bắt cho hổ ăn thịt, vì thế đời cho là vị thần trừ sự không lành, bây giờ hay thờ làm thần coi cửa."
            ],
            "Từ điển Thiều Chửu": [
                "Bờ luỹ, tức là tường chắn trong dinh quân.",
                "Một âm là luật. Uất Luật 鬱壘 tên một vị thần cổ. Ðời thượng cổ có hai anh em là Thần Ðồ 神荼, Uất Luật 鬱壘 kiểm soát loài quỷ làm càn, bắt cho hổ thịt, vì thế đời cho là vị thần trừ sự không lành, bây giờ hay thờ làm thần coi cửa, môn thần 門神."
            ],
            "Từ điển Trần Văn Chánh": [
                "Đắp, xây: 把井口壘高點兒 Đắp cho miệng giếng cao lên tí nữa; 壘一道墻 Xây một bức tường;",
                "(Tường, bờ) luỹ (tường chắn trong doanh trại): 營壘 Đồn luỹ; 壁壘 Thành luỹ; 深溝高壘 Thành cao hào sâu; 兩軍對壘 Hai cánh quân giằng co nhau."
            ],
            "Từ điển Nguyễn Quốc Hùng": [
                "Bức tường cao và day, đắp bằng đất quanh trại quân để ngăn chặn giặc.  Đoạn trường tân thanh  có câu: » Kéo cờ luỹ phát súng thành, Từ công ra ngựa thân nghênh cửa ngoài « — Một âm là Lỗi. Xem Lỗi."
            ],
            "compound_words": {
                "堡壘": "bảo luỹ",
                "壁壘": "bích luỹ",
                "高壘深壁": "cao luỹ thâm bích",
                "屯壘": "đồn luỹ",
                "城壘": "thành luỹ"
            }
        },
        "lỗi": {
            "Từ điển Nguyễn Quốc Hùng": [
                "Đá chồng chất lên nhau — Các âm khác là Luỹ, Luật. Xem các âm này."
            ]
        }
    }
}