{
    "character": "曬",
    "details": {
        "Âm Hán Việt": [
            "sái"
        ],
        "Tổng nét": [
            "23"
        ],
        "Bộ": [
            "nhật 日 (+19 nét)"
        ],
        "Lục thư": [
            "hình thanh"
        ],
        "Hình thái": [
            "⿰日麗"
        ],
        "Nét bút": [
            "丨フ一一一丨フ丶一丨フ丶丶一ノフ丨丨一一フノフ"
        ],
        "Thương Hiệt": [
            "AMMP (日一一心)"
        ],
        "Unicode": [
            "U+66EC"
        ],
        "Độ thông dụng trong Hán ngữ cổ": [
            "trung bình"
        ],
        "Độ thông dụng trong tiếng Trung hiện đại": [
            "cao"
        ],
        "Âm Pinyin": [
            "shài ㄕㄞˋ"
        ],
        "Âm Nôm": [
            "sái"
        ],
        "Âm Nhật (onyomi)": [
            "サイ (sai)",
            "シ (shi)"
        ],
        "Âm Nhật (kunyomi)": [
            "さら (sara)",
            "さらし (sarashi)",
            "さら.す (sara.su)"
        ],
        "Âm Hàn": [
            "쇄"
        ],
        "Âm Quảng Đông": [
            "saai3"
        ]
    },
    "meanings": {
        "sái": {
            "Từ điển phổ thông": [
                "phơi"
            ],
            "Từ điển trích dẫn": [
                "(Động) Phơi, phơi khô. ◇Trương Kế 張繼: 'Mạc sân bồi trà yên ám, Khước hỉ sái cốc thiên tình' 莫嗔焙茶煙暗, 卻喜曬穀天晴 (San gia 山家) Đừng bực sấy trà khói ám, Mà hãy mừng phơi cốc trời tạnh ráo.",
                "(Động) Chiếu, rọi.",
                "(Phó) Rất, lắm, cực.",
                "§ Cũng viết là 晒."
            ],
            "Từ điển Thiều Chửu": [
                "① Phơi."
            ],
            "Từ điển Trần Văn Chánh": [
                "Phơi (nắng), phơi phóng: 曬衣服 Phơi quần áo; 曬太陽 Phơi nắng, tắm nắng, sưởi nắng;",
                "Nắng: 這裡曬得慌 Chỗ này nắng quá."
            ],
            "Từ điển Nguyễn Quốc Hùng": [
                "Phơi ra ánh nắng khô."
            ],
            "compound_words": {
                "曬書": "sái thư"
            }
        }
    }
}