{
    "character": "暦",
    "details": {
        "Âm Hán Việt": [
            "lịch"
        ],
        "Tổng nét": [
            "14"
        ],
        "Bộ": [
            "nhật 日 (+10 nét)"
        ],
        "Lục thư": [
            "hình thanh"
        ],
        "Hình thái": [
            "⿸厂𣈅"
        ],
        "Nét bút": [
            "一ノ一丨ノ丶一丨ノ丶丨フ一一"
        ],
        "Thương Hiệt": [
            "MDDA (一木木日)"
        ],
        "Unicode": [
            "U+66A6"
        ],
        "Độ thông dụng trong Hán ngữ cổ": [
            "rất thấp"
        ],
        "Độ thông dụng trong tiếng Trung hiện đại": [
            "rất thấp"
        ],
        "Âm Pinyin": [
            "lì ㄌㄧˋ"
        ],
        "Âm Nhật (onyomi)": [
            "レキ (reki)"
        ],
        "Âm Nhật (kunyomi)": [
            "こよみ (koyomi)",
            "りゃく (ryaku)"
        ],
        "Âm Hàn": [
            "력"
        ]
    },
    "meanings": {
        "lịch": {
            "Từ điển phổ thông": [
                "trải qua, vượt qua",
                "lịch (như: lịch 曆)"
            ],
            "Từ điển Trần Văn Chánh": [
                "Lịch;",
                "Thời đại;",
                "Tính toán."
            ],
            "Từ điển Nguyễn Quốc Hùng": [
                "Một lối viết giản dị của chữ Lịch 曆."
            ]
        }
    }
}