{
    "character": "槡",
    "details": {
        "Âm Hán Việt": [
            "tang"
        ],
        "Tổng nét": [
            "14"
        ],
        "Bộ": [
            "mộc 木 (+10 nét)"
        ],
        "Hình thái": [
            "⿰木桑"
        ],
        "Nét bút": [
            "一丨ノ丶フ丶フ丶フ丶一丨ノ丶"
        ],
        "Thương Hiệt": [
            "DEED (木水水木)"
        ],
        "Unicode": [
            "U+69E1"
        ],
        "Độ thông dụng trong Hán ngữ cổ": [
            "rất thấp"
        ],
        "Độ thông dụng trong tiếng Trung hiện đại": [
            "rất thấp"
        ],
        "Âm Quảng Đông": [
            "song1"
        ]
    },
    "meanings": {}
}