{
    "character": "清",
    "details": {
        "Âm Hán Việt": [
            "sảnh",
            "thanh"
        ],
        "Tổng nét": [
            "11"
        ],
        "Bộ": [
            "thuỷ 水 (+8 nét)"
        ],
        "Lục thư": [
            "hình thanh"
        ],
        "Hình thái": [
            "⿰⺡青"
        ],
        "Nét bút": [
            "丶丶一一一丨一丨フ一一"
        ],
        "Thương Hiệt": [
            "EQMB (水手一月)"
        ],
        "Unicode": [
            "U+6E05"
        ],
        "Độ thông dụng trong Hán ngữ cổ": [
            "rất cao"
        ],
        "Độ thông dụng trong tiếng Trung hiện đại": [
            "rất cao"
        ],
        "Âm Pinyin": [
            "qīng ㄑㄧㄥ",
            "qìng ㄑㄧㄥˋ"
        ],
        "Âm Nôm": [
            "thanh",
            "thênh",
            "thinh"
        ],
        "Âm Nhật (onyomi)": [
            "セイ (sei)",
            "ショウ (shō)",
            "シン (shin)"
        ],
        "Âm Nhật (kunyomi)": [
            "きよ.い (kiyo.i)",
            "きよ.まる (kiyo.maru)",
            "きよ.める (kiyo.meru)"
        ],
        "Âm Hàn": [
            "청"
        ],
        "Âm Quảng Đông": [
            "ceng1",
            "cing1"
        ]
    },
    "meanings": {
        "sảnh": {
            "Từ điển Nguyễn Quốc Hùng": [
                "Lạnh — Mát — Làm cho mát mẻ. Đáng lẽ đọc Thính."
            ],
            "compound_words": {
                "溫凊": "ôn sảnh"
            }
        },
        "thanh": {
            "Từ điển phổ thông": [
                "trong sạch (nước)",
                "đời nhà Thanh",
                "họ Thanh"
            ],
            "Từ điển trích dẫn": [
                "(Tính) Trong. Trái với 'trọc' 濁 đục. ◎Như: 'thanh triệt' 清澈 trong suốt.",
                "(Tính) Trong sạch, liêm khiết, cao khiết. ◎Như: 'thanh bạch' 清白, 'thanh tháo' 清操, 'thanh tiết' 清節.",
                "(Tính) Mát. ◎Như: 'thanh phong minh nguyệt' 清風明月 gió mát trăng trong.",
                "(Tính) Lặng, vắng. ◎Như: 'thanh dạ' 清夜 đêm lặng, 'thanh tĩnh' 清靜 vắng lặng.",
                "(Tính) Rõ ràng, minh bạch. ◎Như: 'thanh sở' 清楚 rõ ràng.",
                "(Tính) Xinh đẹp, tú mĩ. ◎Như: 'mi thanh mục tú' 眉清目秀 mày xinh mắt đẹp.",
                "(Tính) Yên ổn, thái bình. ◎Như: 'thanh bình thịnh thế' 清平盛世 đời thái bình thịnh vượng.",
                "(Phó) Suông, thuần, đơn thuần. ◎Như: 'thanh nhất sắc' 清一色 thuần một màu, 'thanh xướng' 清唱 diễn xướng không hóa trang, 'thanh đàm' 清談 bàn suông.",
                "(Phó) Hết, xong, sạch trơn. ◎Như: 'trái hoàn thanh liễu' 債還清了 nợ trả xong hết.",
                "(Phó) Rõ ràng, minh bạch, kĩ lưỡng. ◎Như: 'điểm thanh số mục' 點清數目 kiểm điểm số mục rõ ràng, 'tra thanh hộ khẩu' 查清戶口 kiểm tra kĩ càng hộ khẩu.",
                "(Động) Làm cho sạch, làm cho ngay ngắn chỉnh tề. ◎Như: 'thanh tẩy' 清洗 rửa sạch, tẩy trừ, 'thanh lí' 清理 lọc sạch, 'thanh trừ' 清除 quét sạch, dọn sạch.",
                "(Động) Làm xong, hoàn tất. ◎Như: 'thanh trướng' 清帳 trả sạch nợ, 'thanh toán' 清算 tính xong hết (sổ sách, trương mục), kết toán.",
                "(Động) Soát, kiểm kê. ◎Như: 'thanh điểm nhân số' 清點人數 kiểm kê số người.",
                "(Danh) Không hư. ◎Như: 'thái thanh' 太清 chỗ trời không, chốn hư không.",
                "(Danh) Nhà 'Thanh'.",
                "(Danh) Họ 'Thanh'."
            ],
            "Từ điển Thiều Chửu": [
                "Trong, nước không có chút cặn nào gọi là thanh.",
                "Sạch, không thèm làm những sự không đáng làm gọi là thanh bạch 清白, là thanh tháo 清操, thanh tiết 清節, v.v.",
                "Sửa sang rành mạch, như thanh li 清釐, thanh lí 清理, v.v.",
                "Giản lược, như chánh giản hình thanh 政簡刑清 chánh trị hình phép giản dị.",
                "Không hư, như thái thanh 太清 chỗ trời không, chốn hư không có một vật gì.",
                "Kết liễu, như thanh ngật 清 sổ sách tính xong hết.",
                "Nhà Thanh.",
                "Lặng, như thanh dạ 清夜 đêm lặng."
            ],
            "Từ điển Trần Văn Chánh": [
                "Trong: 水清見底 Nước trong vắt;",
                "Sạch: 洗清污濁 Gột sạch những dơ bẩn;",
                "Mát: 清風明月 Gió mát trăng thanh;",
                "Liêm khiết, thanh liêm, trong sạch: 清官 Quan lại liêm khiết;",
                "Rõ: 把話問清 Hỏi cho rõ;",
                "Hết, xong: 把帳還清 Trả hết nợå;",
                "Thanh lọc: 把壞份子清出去 Thanh lọc những phần tử xấu;",
                "Lặng, thanh vắng: 清夜 Đêm vắng;",
                "[Qing] Đời nhà Thanh (Trung Quốc, 1644—1911);",
                "[Qing] (Họ) Thanh."
            ],
            "Từ điển Nguyễn Quốc Hùng": [
                "Nước yên lặng — Yên lặng. Td: Thanh bình — Sạch sẽ. Trong sạch. Td: Thanh khiết — Lo việc cho sạch, cho xong. Truyện  Trê Cóc : » Truyền Trê phải chịu cho thanh mọi bề « — Sáng sủa.  Đoạn trường tân thanh : » Lần thâu gió mát trăng thanh « — Ta còn hiểu là mát mẻ. Truyện  Hoa Tiên » Gió thanh hây hẩy gác vàng « — Tên một triều đại Trung Hoa, gồm 9 đời 10 vua, kéo dài 268 năm ( 1644-1911 ) — Đẹp đẽ cao quý.  Đoạn trường tân thanh » Khác màu kẻ quý người thanh «."
            ],
            "compound_words": {
                "冰清玉潔": "băng thanh ngọc khiết",
                "血清": "huyết thanh",
                "滿清": "mãn thanh",
                "眉清目秀": "mi thanh mục tú",
                "掃清": "tảo thanh",
                "清白": "thanh bạch",
                "清貧": "thanh bần",
                "清平": "thanh bình",
                "清高": "thanh cao",
                "清蒸": "thanh chưng",
                "清夜": "thanh dạ",
                "清名": "thanh danh",
                "清遊": "thanh du",
                "清淡": "thanh đạm",
                "清軒前後集": "thanh hiên tiền hậu tập",
                "清化": "thanh hoá",
                "清客": "thanh khách",
                "清潔": "thanh khiết",
                "清歴": "thanh lịch",
                "清廉": "thanh liêm",
                "清浰": "thanh lợi",
                "清明": "thanh minh",
                "清議": "thanh nghị",
                "清雅": "thanh nhã",
                "清閒": "thanh nhàn",
                "清風": "thanh phong",
                "清光": "thanh quang",
                "清楚": "thanh sở",
                "清騷": "thanh tao",
                "清心": "thanh tâm",
                "清新": "thanh tân",
                "清水": "thanh thuỷ",
                "清脆": "thanh thuý",
                "清淨": "thanh tịnh",
                "清算": "thanh toán",
                "清除": "thanh trừ",
                "清秀": "thanh tú",
                "十清九濁": "thập thanh cửu trọc",
                "澄清": "trừng thanh"
            }
        }
    }
}