{
    "character": "濥",
    "details": {
        "Âm Hán Việt": [
            "dần"
        ],
        "Tổng nét": [
            "17"
        ],
        "Bộ": [
            "thuỷ 水 (+14 nét)"
        ],
        "Hình thái": [
            "⿰⺡夤"
        ],
        "Nét bút": [
            "丶丶一ノフ丶丶丶フ一丨フ一丨一ノ丶"
        ],
        "Thương Hiệt": [
            "ENIC (水弓戈金)"
        ],
        "Unicode": [
            "U+6FE5"
        ],
        "Độ thông dụng trong Hán ngữ cổ": [
            "rất thấp"
        ],
        "Độ thông dụng trong tiếng Trung hiện đại": [
            "rất thấp"
        ],
        "Âm Hàn": [
            "인"
        ]
    },
    "meanings": {}
}