{
    "character": "濪",
    "details": {
        "Tổng nét": [
            "17"
        ],
        "Bộ": [
            "thuỷ 水 (+14 nét)"
        ],
        "Hình thái": [
            "⿰⺡靘"
        ],
        "Nét bút": [
            "丶丶一一一丨一丨フ一一ノフフ丨一フ"
        ],
        "Thương Hiệt": [
            "EQBU (水手月山)"
        ],
        "Unicode": [
            "U+6FEA"
        ],
        "Độ thông dụng trong Hán ngữ cổ": [
            "rất thấp"
        ],
        "Độ thông dụng trong tiếng Trung hiện đại": [
            "rất thấp"
        ]
    },
    "meanings": {}
}