{
    "character": "馬",
    "details": {
        "Âm Hán Việt": [
            "mã"
        ],
        "Tổng nét": [
            "10"
        ],
        "Bộ": [
            "mã 馬 (+0 nét)"
        ],
        "Lục thư": [
            "tượng hình"
        ],
        "Nét bút": [
            "一丨一一丨フ丶丶丶丶"
        ],
        "Thương Hiệt": [
            "SQSF (尸手尸火)"
        ],
        "Unicode": [
            "U+99AC"
        ],
        "Độ thông dụng trong Hán ngữ cổ": [
            "rất cao"
        ],
        "Độ thông dụng trong tiếng Trung hiện đại": [
            "rất cao"
        ],
        "Âm Pinyin": [
            "mǎ ㄇㄚˇ"
        ],
        "Âm Nôm": [
            "mã",
            "mở",
            "mứa"
        ],
        "Âm Nhật (onyomi)": [
            "バ (ba)"
        ],
        "Âm Nhật (kunyomi)": [
            "うま (uma)",
            "うま- (uma-)",
            "ま (ma)"
        ],
        "Âm Hàn": [
            "마"
        ],
        "Âm Quảng Đông": [
            "maa5"
        ]
    },
    "meanings": {
        "mã": {
            "Từ điển phổ thông": [
                "con ngựa"
            ],
            "Từ điển trích dẫn": [
                "(Danh) Ngựa. ◇Nguyễn Du 阮攸: 'Thùy gia lão mã khí thành âm' 誰家老馬棄城陰 (Thành hạ khí mã 城下棄馬) Con ngựa già nhà ai bỏ dưới bóng thành.",
                "(Danh) Cái thẻ ghi số đếm. § Thông 'mã' 碼. Ghi chú: Chữ cổ viết là 'mã' 碼, là cái thẻ ngày xưa dùng ghi số trong trò chơi 'đầu hồ' 投壺. Ngày nay, 'mã' chỉ kí hiệu ghi số. ◎Như: 'hiệu mã' 號馬 số hiệu.",
                "(Danh) Kị binh. ◇Bắc Tề Thư 北齊書: 'Thì (Thần Vũ quân) mã bất mãn nhị thiên, bộ binh bất chí tam vạn, chúng quả bất địch' 時(神武軍)馬不滿二千, 步兵不至三萬，眾寡不敵 (Thần Vũ đế kỉ thượng 神武帝紀上).",
                "(Danh) Việc binh, vũ sự. ◇Chu Lễ 周禮: 'Hạ quan tư mã' 夏官司馬 (Hạ quan 夏官, Tự quan 序官).",
                "(Danh) Họ 'Mã'.",
                "(Động) Đóng ngựa. ◇Liêu trai chí dị 聊齋志異: 'Nhất xuất môn, cừu mã quá thế gia yên' 一出門, 裘馬過世家焉 (Xúc chức 促織) Mỗi khi ra ngoài, mặc áo cừu đóng xe ngựa (sang trọng) còn hơn cả bậc thế gia.",
                "(Động) Đè ép, áp chế (phương ngôn). ◇Lí Cật Nhân 李劼人: 'Nã xuất thoại lai bả chúng nhân mã trụ' 拿出話來把眾人馬住 (Tử thủy vi lan 死水微瀾, Đệ ngũ bộ phân thập tứ 第五部分十四).",
                "(Động) Nhắm, nhìn chăm chú (phương ngôn).",
                "(Phó) Hình dung tỏ vẻ nghiêm khắc, giận dữ... (kéo dài mặt ra như mặt ngựa). ◇Sa Đinh 沙汀: '(Lão bà) thán khẩu khí thuyết: Khán nhĩ mã khởi trương kiểm' (老婆)嘆口氣說: 看你馬起張臉 (Giảm tô 減租).",
                "(Tính) To, lớn. ◎Như: 'mã phong' 馬蜂 ong vẽ, 'mã đậu' 馬豆 đậu to."
            ],
            "Từ điển Thiều Chửu": [
                "Con ngựa. Xem tướng ngựa phải xem răng trước, vì thế nên nói nhún số tuổi của mình cũng kêu là mã xỉ 馬齒.",
                "Cái thẻ ghi số đếm.",
                "Họ Mã."
            ],
            "Từ điển Trần Văn Chánh": [
                "Ngựa: 母馬 Ngựa cái; 種馬 Ngựa đực, ngựa giống. 【馬騾】mã loa [măluó] Con la;",
                "To, lớn: 馬蜂 Ong vẽ, ong bắp cày;",
                "(văn) Thẻ ghi số đếm;",
                "[Mă] (Họ) Mã."
            ],
            "Từ điển Nguyễn Quốc Hùng": [
                "Con ngựa. Loài ngựa — Tên gọi đồng bạc của Đức quốc trước năm 2002, tức đồng Mã — Tên một trong các bộ chữ Trung Hoa."
            ],
            "compound_words": {
                "亞拉巴馬": "á lạp ba mã",
                "阿拉巴馬": "a lạp ba mã",
                "鞍馬": "an mã",
                "奧克拉荷馬": "áo khắc lạp hà mã",
                "巴拿馬": "ba nã mã",
                "巴拿馬運河": "ba nã mã vận hà",
                "斑馬": "ban mã",
                "班馬": "ban mã",
                "盤馬彎弓": "bàn mã loan cung",
                "兵馬": "binh mã",
                "競馬場": "cạnh mã trường",
                "狗馬": "cẩu mã",
                "狗馬之心": "cẩu mã chi tâm",
                "指鹿為馬": "chỉ lộc vi mã",
                "裘馬": "cừu mã",
                "野馬": "dã mã",
                "驛馬": "dịch mã",
                "特洛伊木馬": "đặc lạc y mộc mã",
                "騰馬": "đằng mã",
                "墮馬": "đoạ mã",
                "下馬": "hạ mã",
                "河馬": "hà mã",
                "汗馬": "hãn mã",
                "叩馬": "khấu mã",
                "扣馬而諫": "khấu mã nhi gián",
                "快馬": "khoái mã",
                "犬馬": "khuyển mã",
                "騎馬": "kị mã",
                "羅馬": "la mã",
                "馬棚": "mã bằng",
                "馬革": "mã cách",
                "馬桶": "mã dũng",
                "馬蹄": "mã đề",
                "馬蛭": "mã điệt",
                "馬虎": "mã hổ",
                "馬蚿": "mã huyền",
                "馬克": "mã khắc",
                "馬來": "mã lai",
                "馬勒": "mã lặc",
                "馬路": "mã lộ",
                "馬力": "mã lực",
                "馬牛": "mã ngưu",
                "馬夫": "mã phu",
                "馬首欲東": "mã thủ dục đông",
                "馬上": "mã thượng",
                "馬鞭": "mã tiên",
                "馬哨": "mã tiếu",
                "馬尾": "mã vĩ",
                "馬車": "mã xa",
                "母馬": "mẫu mã",
                "牛頭馬面": "ngưu đầu mã diện",
                "人馬": "nhân mã",
                "烏馬": "ô mã",
                "樸馬": "phác mã",
                "肥馬": "phì mã",
                "扇馬": "phiến mã",
                "駙馬": "phụ mã",
                "郡馬": "quận mã",
                "郡駙馬": "quận phò mã",
                "雙馬": "song mã",
                "塞翁失馬": "tái ông thất mã",
                "散馬": "tản mã",
                "走馬": "tẩu mã",
                "上馬": "thượng mã",
                "賽馬": "trại mã",
                "駿馬": "tuấn mã",
                "車馬": "xa mã",
                "倚馬": "ỷ mã",
                "意馬": "ý mã"
            }
        }
    }
}